hasmtools/__init__.py
hasmtools/cli.py
hasmtools/util/__init__.py
hasmtools/util/dot.py
hasmtools/util/json.py
hasmtools/util/types.py
hasmtools/util/yaml.py
hasmtools-0.0.3.dist-info/LICENSE
hasmtools-0.0.3.dist-info/METADATA
hasmtools-0.0.3.dist-info/WHEEL
hasmtools-0.0.3.dist-info/entry_points.txt
hasmtools-0.0.3.dist-info/top_level.txt
hasmtools-0.0.3.dist-info/RECORD
