Metadata-Version: 2.1
Name: hasmtools
Version: 0.0.3
Summary: Visualize Home Assistant Finite State Machines
Author-email: Florian Streibelt <mail+github@yakshaving.de>
License: Apache-2.0
Project-URL: Documentation, https://github.com/mutax/hasmtools
Project-URL: Source, https://github.com/mutax/hasmtools
Project-URL: Changelog, https://github.com/mutax/hasmtools/CHANGES
Keywords: HomeAssistant,FSM
Classifier: Programming Language :: Python :: 3
Classifier: Development Status :: 4 - Beta
Requires-Python: >=3.11
License-File: LICENSE
Requires-Dist: click>=8.1.7
Requires-Dist: pydot>=3.0.3
Requires-Dist: PyYAML>=6.0.2
